{"SURVIVAL":{"inventoryContents":{"11":{"==":"org.bukkit.inventory.ItemStack","type":"BOW"},"12":{"==":"org.bukkit.inventory.ItemStack","type":"COMPASS","amount":64},"13":{"==":"org.bukkit.inventory.ItemStack","type":"WATCH","amount":64},"14":{"==":"org.bukkit.inventory.ItemStack","type":"IRON_INGOT","amount":2},"0":{"==":"org.bukkit.inventory.ItemStack","type":"WRITTEN_BOOK","meta":{"==":"ItemMeta","meta-type":"BOOK_SIGNED","display-name":"§a§lMENU","lore":["§6Сайт авто-доната :"],"title":" ","author":" ","generation":0}},"1":{"==":"org.bukkit.inventory.ItemStack","type":"BONE","meta":{"==":"ItemMeta","meta-type":"UNSPECIFIC","display-name":"§c§lDONATE","lore":["§6Сайт авто-доната :"]}},"2":{"==":"org.bukkit.inventory.ItemStack","type":"RED_ROSE","meta":{"==":"ItemMeta","meta-type":"UNSPECIFIC","display-name":"§9§lSHOP","lore":["§6Сайт авто-доната :"]}},"3":{"==":"org.bukkit.inventory.ItemStack","type":"DOUBLE_PLANT","meta":{"==":"ItemMeta","meta-type":"UNSPECIFIC","display-name":"§b§lLOBBY","lore":["§6Сайт авто-доната :"]}},"4":{"==":"org.bukkit.inventory.ItemStack","type":"REDSTONE","amount":4},"5":{"==":"org.bukkit.inventory.ItemStack","type":"LEVER"},"6":{"==":"org.bukkit.inventory.ItemStack","type":"GLASS"},"7":{"==":"org.bukkit.inventory.ItemStack","type":"CARPET","damage":14},"8":{"==":"org.bukkit.inventory.ItemStack","type":"WATCH","meta":{"==":"ItemMeta","meta-type":"UNSPECIFIC","display-name":"§e§lADMIN MENU","lore":["§6Все для вас парни"]}},"9":{"==":"org.bukkit.inventory.ItemStack","type":"LEATHER"},"10":{"==":"org.bukkit.inventory.ItemStack","type":"DIAMOND_SWORD"}},"enderChestContents":{},"armorContents":{},"potions":"[]","stats":{"ex":"0.046899997","ma":"300","fl":"20","el":"1","xp":"0.46913588","hp":"20.0","txp":"20","sa":"10.0","fd":"0.0","ft":"-20","ra":"300"}}}